odoo/addons/fieldservice_stock_scrap/README.rst
odoo/addons/fieldservice_stock_scrap/__init__.py
odoo/addons/fieldservice_stock_scrap/__manifest__.py
odoo/addons/fieldservice_stock_scrap/data/stock_location.xml
odoo/addons/fieldservice_stock_scrap/i18n/ca.po
odoo/addons/fieldservice_stock_scrap/i18n/es.po
odoo/addons/fieldservice_stock_scrap/i18n/fieldservice_stock_scrap.pot
odoo/addons/fieldservice_stock_scrap/i18n/it.po
odoo/addons/fieldservice_stock_scrap/models/__init__.py
odoo/addons/fieldservice_stock_scrap/models/fsm_order.py
odoo/addons/fieldservice_stock_scrap/models/stock_scrap.py
odoo/addons/fieldservice_stock_scrap/readme/CONTRIBUTORS.md
odoo/addons/fieldservice_stock_scrap/readme/DESCRIPTION.md
odoo/addons/fieldservice_stock_scrap/readme/USAGE.md
odoo/addons/fieldservice_stock_scrap/security/ir.model.access.csv
odoo/addons/fieldservice_stock_scrap/static/description/icon.png
odoo/addons/fieldservice_stock_scrap/static/description/index.html
odoo/addons/fieldservice_stock_scrap/tests/__init__.py
odoo/addons/fieldservice_stock_scrap/tests/test_stock_scrap.py
odoo/addons/fieldservice_stock_scrap/views/fsm_order.xml
odoo/addons/fieldservice_stock_scrap/views/stock_scrap.xml
odoo/addons/fieldservice_stock_scrap/wizards/__init__.py
odoo/addons/fieldservice_stock_scrap/wizards/scrap_stock_wizard.py
odoo/addons/fieldservice_stock_scrap/wizards/scrap_stock_wizard.xml
odoo_addon_fieldservice_stock_scrap-17.0.1.2.0.dist-info/METADATA
odoo_addon_fieldservice_stock_scrap-17.0.1.2.0.dist-info/WHEEL
odoo_addon_fieldservice_stock_scrap-17.0.1.2.0.dist-info/top_level.txt
odoo_addon_fieldservice_stock_scrap-17.0.1.2.0.dist-info/RECORD
