Metadata-Version: 2.1
Name: odoo-addon-fieldservice_stock_scrap
Version: 17.0.1.2.0
Requires-Python: >=3.10
Requires-Dist: odoo-addon-fieldservice_stock_request>=17.0dev,<17.1dev
Requires-Dist: odoo>=17.0a,<17.1dev
Summary: Scrap stock from Field Service order of Stock Requests
Home-page: https://github.com/OCA/field-service
License: AGPL-3
Author: Antoni Marroig, APSL-Nagarro, Odoo Community Association (OCA)
Author-email: support@odoo-community.org
Classifier: Programming Language :: Python
Classifier: Framework :: Odoo
Classifier: Framework :: Odoo :: 17.0
Classifier: License :: OSI Approved :: GNU Affero General Public License v3
